geo_upload_tool/__init__.py
geo_upload_tool/geo_upload_tool.py
geo_upload_tool/gut.snake
geo_upload_tool/version.py
geo_upload_tool-1.0.8.dist-info/DESCRIPTION.rst
geo_upload_tool-1.0.8.dist-info/METADATA
geo_upload_tool-1.0.8.dist-info/RECORD
geo_upload_tool-1.0.8.dist-info/WHEEL
geo_upload_tool-1.0.8.dist-info/entry_points.txt
geo_upload_tool-1.0.8.dist-info/metadata.json
geo_upload_tool-1.0.8.dist-info/top_level.txt
